{
  "progress": true,
  "navigation": {
    "logo": "./media/ct-logo.png"
  },
  "aside": {},
  "sections": [
    {
      "modules": [
        {
          "type": "contribute",
          "id": "subpage-contribute",
          "title": "Contribute",
          "subtitle": "Data from your company, lab or organization can change the way the world uses data to decarbonize. Check out the library of data that powers Climate TRACE today and contact us with your contribution."
        },
        {
          "type": "subscribe"
        },
        {
          "type": "footer",
          "grid": true
        }
      ]
    }
  ]
}